context_enriched_chunking/__init__.py
context_enriched_chunking-0.1.3.dist-info/METADATA
context_enriched_chunking-0.1.3.dist-info/WHEEL
context_enriched_chunking-0.1.3.dist-info/top_level.txt
context_enriched_chunking-0.1.3.dist-info/RECORD
