Metadata-Version: 2.4
Name: context_enriched_chunking
Version: 0.1.3
Summary: A text chunking strategy that keeps document title and section as headers for each chunk.
Home-page: https://github.com/alvelvis/context-enriched-chunking
Author: Elvis A. de Souza
Author-email: "Elvis A. de Souza" <elvis.desouza99@gmail.com>
Project-URL: Homepage, https://github.com/alvelvis/context-enriched-chunking
Requires-Python: >=3.6
Requires-Dist: langchain-text-splitters
Dynamic: author
Dynamic: home-page
Dynamic: requires-python
